arz_api/__init__.py
arz_api/api.py
arz_api/consts.py
arz_api/exceptions.py
arz_api/bypass_antibot/__init__.py
arz_api/bypass_antibot/script.py
arz_api/models/__init__.py
arz_api/models/category_object.py
arz_api/models/member_object.py
arz_api/models/other.py
arz_api/models/post_object.py
arz_api/models/thread_object.py
arz_api-2.2.dist-info/licenses/LICENSE
arz_api-2.2.dist-info/METADATA
arz_api-2.2.dist-info/WHEEL
arz_api-2.2.dist-info/top_level.txt
arz_api-2.2.dist-info/RECORD
